{"cpu_time": 0.0, "wallclock_time": 0.029083251953125, "evaluations": 0, "cost": 2147483648, "incumbent": {"autovacuum": "on", "autovacuum_analyze_scale_factor": 92.54951484416927, "autovacuum_analyze_threshold": 680, "autovacuum_freeze_max_age": 637165486, "autovacuum_max_workers": 5613, "autovacuum_multixact_freeze_max_age": 1704484194, "autovacuum_naptime": 1751646, "autovacuum_vacuum_cost_delay": 49, "autovacuum_vacuum_cost_limit": 3471, "autovacuum_vacuum_scale_factor": 21.225249416995478, "autovacuum_vacuum_threshold": 554940970, "autovacuum_work_mem": 668311, "backend_flush_after": 160, "bgwriter_delay": 1812, "bgwriter_flush_after": 252, "bgwriter_lru_maxpages": 524, "bgwriter_lru_multiplier": 5.758713934191293, "checkpoint_completion_target": 0.6625856558758222, "checkpoint_flush_after": 43, "checkpoint_timeout": 49087, "commit_delay": 2853, "commit_siblings": 16, "cpu_index_tuple_cost": 0.3026943699392084, "cpu_operator_cost": 3.4270452549212678, "cpu_tuple_cost": 2.35081618632005, "cursor_tuple_fraction": 0.8573125030993033, "data_sync_retry": "off", "deadlock_timeout": 2680, "default_statistics_target": 4521, "default_transaction_deferrable": "off", "effective_cache_size": 1722772, "effective_io_concurrency": 192, "enable_bitmapscan": "on", "enable_hashagg": "off", "enable_hashjoin": "on", "enable_indexonlyscan": "on", "enable_indexscan": "off", "enable_material": "off", "enable_mergejoin": "off", "enable_nestloop": "off", "enable_seqscan": "on", "enable_sort": "off", "enable_tidscan": "on", "from_collapse_limit": 50, "full_page_writes": "off", "geqo": "off", "geqo_effort": 4, "geqo_generations": 215, "geqo_pool_size": 910, "geqo_seed": 0.8441731634122298, "geqo_selection_bias": 1.8821496127762218, "geqo_threshold": 9, "join_collapse_limit": 19, "maintenance_work_mem": 434659, "max_connections": 3347, "max_files_per_process": 25306, "max_locks_per_transaction": 550, "max_parallel_workers_per_gather": 234, "max_pred_locks_per_transaction": 412, "max_prepared_transactions": 407, "max_stack_depth": 4494, "max_wal_size": 73, "max_worker_processes": 209, "min_parallel_relation_size": 21720, "min_wal_size": 3, "old_snapshot_threshold": 45166, "parallel_setup_cost": 2233.379201052889, "parallel_tuple_cost": 0.9976646509554085, "quote_all_identifiers": "off", "random_page_cost": 1.3765312575742927, "replacement_sort_tuples": 782275809, "seq_page_cost": 0.3659546604570384, "shared_buffers": 892821, "temp_buffers": 30554, "temp_file_limit": 1973599, "vacuum_cost_delay": 55, "vacuum_cost_limit": 4192, "vacuum_cost_page_dirty": 7986, "vacuum_cost_page_hit": 3217, "vacuum_cost_page_miss": 481, "vacuum_freeze_min_age": 213165693, "vacuum_freeze_table_age": 1463988470, "vacuum_multixact_freeze_min_age": 35022117, "vacuum_multixact_freeze_table_age": 1924516743, "wal_buffers": 19112, "wal_compression": "off", "wal_log_hints": "on", "wal_writer_delay": 2701, "wal_writer_flush_after": 9884, "work_mem": 252124}, "budget": 0, "origin": "LHD"}
{"cpu_time": 84.07740521430969, "wallclock_time": 84.1175787448883, "evaluations": 1, "cost": -696.669636, "incumbent": {"autovacuum": "on", "autovacuum_analyze_scale_factor": 92.54951484416927, "autovacuum_analyze_threshold": 680, "autovacuum_freeze_max_age": 637165486, "autovacuum_max_workers": 5613, "autovacuum_multixact_freeze_max_age": 1704484194, "autovacuum_naptime": 1751646, "autovacuum_vacuum_cost_delay": 49, "autovacuum_vacuum_cost_limit": 3471, "autovacuum_vacuum_scale_factor": 21.225249416995478, "autovacuum_vacuum_threshold": 554940970, "autovacuum_work_mem": 668311, "backend_flush_after": 160, "bgwriter_delay": 1812, "bgwriter_flush_after": 252, "bgwriter_lru_maxpages": 524, "bgwriter_lru_multiplier": 5.758713934191293, "checkpoint_completion_target": 0.6625856558758222, "checkpoint_flush_after": 43, "checkpoint_timeout": 49087, "commit_delay": 2853, "commit_siblings": 16, "cpu_index_tuple_cost": 0.3026943699392084, "cpu_operator_cost": 3.4270452549212678, "cpu_tuple_cost": 2.35081618632005, "cursor_tuple_fraction": 0.8573125030993033, "data_sync_retry": "off", "deadlock_timeout": 2680, "default_statistics_target": 4521, "default_transaction_deferrable": "off", "effective_cache_size": 1722772, "effective_io_concurrency": 192, "enable_bitmapscan": "on", "enable_hashagg": "off", "enable_hashjoin": "on", "enable_indexonlyscan": "on", "enable_indexscan": "off", "enable_material": "off", "enable_mergejoin": "off", "enable_nestloop": "off", "enable_seqscan": "on", "enable_sort": "off", "enable_tidscan": "on", "from_collapse_limit": 50, "full_page_writes": "off", "geqo": "off", "geqo_effort": 4, "geqo_generations": 215, "geqo_pool_size": 910, "geqo_seed": 0.8441731634122298, "geqo_selection_bias": 1.8821496127762218, "geqo_threshold": 9, "join_collapse_limit": 19, "maintenance_work_mem": 434659, "max_connections": 3347, "max_files_per_process": 25306, "max_locks_per_transaction": 550, "max_parallel_workers_per_gather": 234, "max_pred_locks_per_transaction": 412, "max_prepared_transactions": 407, "max_stack_depth": 4494, "max_wal_size": 73, "max_worker_processes": 209, "min_parallel_relation_size": 21720, "min_wal_size": 3, "old_snapshot_threshold": 45166, "parallel_setup_cost": 2233.379201052889, "parallel_tuple_cost": 0.9976646509554085, "quote_all_identifiers": "off", "random_page_cost": 1.3765312575742927, "replacement_sort_tuples": 782275809, "seq_page_cost": 0.3659546604570384, "shared_buffers": 892821, "temp_buffers": 30554, "temp_file_limit": 1973599, "vacuum_cost_delay": 55, "vacuum_cost_limit": 4192, "vacuum_cost_page_dirty": 7986, "vacuum_cost_page_hit": 3217, "vacuum_cost_page_miss": 481, "vacuum_freeze_min_age": 213165693, "vacuum_freeze_table_age": 1463988470, "vacuum_multixact_freeze_min_age": 35022117, "vacuum_multixact_freeze_table_age": 1924516743, "wal_buffers": 19112, "wal_compression": "off", "wal_log_hints": "on", "wal_writer_delay": 2701, "wal_writer_flush_after": 9884, "work_mem": 252124}, "budget": 0, "origin": "LHD"}
{"cpu_time": 170.49750447273254, "wallclock_time": 170.54936599731445, "evaluations": 2, "cost": -703.215431, "incumbent": {"autovacuum": "off", "autovacuum_analyze_scale_factor": 87.58499486494557, "autovacuum_analyze_threshold": 440, "autovacuum_freeze_max_age": 338231297, "autovacuum_max_workers": 3243, "autovacuum_multixact_freeze_max_age": 1409796625, "autovacuum_naptime": 1222607, "autovacuum_vacuum_cost_delay": 20, "autovacuum_vacuum_cost_limit": 7037, "autovacuum_vacuum_scale_factor": 61.174927253229015, "autovacuum_vacuum_threshold": 1526077753, "autovacuum_work_mem": 777668, "backend_flush_after": 81, "bgwriter_delay": 874, "bgwriter_flush_after": 23, "bgwriter_lru_maxpages": 248, "bgwriter_lru_multiplier": 3.316265816891608, "checkpoint_completion_target": 0.7275455827739518, "checkpoint_flush_after": 222, "checkpoint_timeout": 86119, "commit_delay": 3843, "commit_siblings": 7, "cpu_index_tuple_cost": 3.4100069266426383, "cpu_operator_cost": 2.1736948555704543, "cpu_tuple_cost": 3.758438918722592, "cursor_tuple_fraction": 0.5098373631860147, "data_sync_retry": "off", "deadlock_timeout": 1645, "default_statistics_target": 170, "default_transaction_deferrable": "off", "effective_cache_size": 1444474, "effective_io_concurrency": 231, "enable_bitmapscan": "off", "enable_hashagg": "off", "enable_hashjoin": "on", "enable_indexonlyscan": "on", "enable_indexscan": "on", "enable_material": "off", "enable_mergejoin": "off", "enable_nestloop": "on", "enable_seqscan": "off", "enable_sort": "off", "enable_tidscan": "on", "from_collapse_limit": 31, "full_page_writes": "off", "geqo": "off", "geqo_effort": 2, "geqo_generations": 632, "geqo_pool_size": 778, "geqo_seed": 0.37476743251636485, "geqo_selection_bias": 1.7920921399450906, "geqo_threshold": 22, "join_collapse_limit": 37, "maintenance_work_mem": 602117, "max_connections": 1572, "max_files_per_process": 15571, "max_locks_per_transaction": 742, "max_parallel_workers_per_gather": 224, "max_pred_locks_per_transaction": 139, "max_prepared_transactions": 470, "max_stack_depth": 3437, "max_wal_size": 159, "max_worker_processes": 20, "min_parallel_relation_size": 75969, "min_wal_size": 4, "old_snapshot_threshold": 30160, "parallel_setup_cost": 946.1659758067328, "parallel_tuple_cost": 2.1239178720370173, "quote_all_identifiers": "on", "random_page_cost": 7.41042183199986, "replacement_sort_tuples": 584104972, "seq_page_cost": 3.0938895616455007, "shared_buffers": 90115, "temp_buffers": 5793, "temp_file_limit": 2919105, "vacuum_cost_delay": 27, "vacuum_cost_limit": 8774, "vacuum_cost_page_dirty": 1719, "vacuum_cost_page_hit": 7363, "vacuum_cost_page_miss": 6566, "vacuum_freeze_min_age": 632385476, "vacuum_freeze_table_age": 696963060, "vacuum_multixact_freeze_min_age": 611569434, "vacuum_multixact_freeze_table_age": 651920247, "wal_buffers": 48379, "wal_compression": "on", "wal_log_hints": "off", "wal_writer_delay": 4075, "wal_writer_flush_after": 16435, "work_mem": 34955}, "budget": 0, "origin": "LHD"}
{"cpu_time": 2531.8404693603516, "wallclock_time": 2706.63400554657, "evaluations": 19, "cost": -716.946253, "incumbent": {"autovacuum": "off", "autovacuum_analyze_scale_factor": 87.58499486494557, "autovacuum_analyze_threshold": 373, "autovacuum_freeze_max_age": 338231297, "autovacuum_max_workers": 3243, "autovacuum_multixact_freeze_max_age": 1438563651, "autovacuum_naptime": 1222607, "autovacuum_vacuum_cost_delay": 34, "autovacuum_vacuum_cost_limit": 7341, "autovacuum_vacuum_scale_factor": 61.174927253229015, "autovacuum_vacuum_threshold": 1435713791, "autovacuum_work_mem": 792060, "backend_flush_after": 81, "bgwriter_delay": 874, "bgwriter_flush_after": 23, "bgwriter_lru_maxpages": 241, "bgwriter_lru_multiplier": 3.316265816891608, "checkpoint_completion_target": 0.7275455827739518, "checkpoint_flush_after": 222, "checkpoint_timeout": 86119, "commit_delay": 4027, "commit_siblings": 16, "cpu_index_tuple_cost": 3.4100069266426383, "cpu_operator_cost": 2.2935369748434726, "cpu_tuple_cost": 3.758438918722592, "cursor_tuple_fraction": 0.5098373631860147, "data_sync_retry": "off", "deadlock_timeout": 2545, "default_statistics_target": 191, "default_transaction_deferrable": "off", "effective_cache_size": 1444474, "effective_io_concurrency": 231, "enable_bitmapscan": "off", "enable_hashagg": "off", "enable_hashjoin": "off", "enable_indexonlyscan": "on", "enable_indexscan": "on", "enable_material": "off", "enable_mergejoin": "off", "enable_nestloop": "off", "enable_seqscan": "off", "enable_sort": "off", "enable_tidscan": "on", "from_collapse_limit": 31, "full_page_writes": "off", "geqo": "off", "geqo_effort": 3, "geqo_generations": 632, "geqo_pool_size": 778, "geqo_seed": 0.43441308899014924, "geqo_selection_bias": 1.8038121642570655, "geqo_threshold": 22, "join_collapse_limit": 41, "maintenance_work_mem": 602117, "max_connections": 198, "max_files_per_process": 15701, "max_locks_per_transaction": 742, "max_parallel_workers_per_gather": 243, "max_pred_locks_per_transaction": 139, "max_prepared_transactions": 470, "max_stack_depth": 3200, "max_wal_size": 159, "max_worker_processes": 32, "min_parallel_relation_size": 70960, "min_wal_size": 4, "old_snapshot_threshold": 30430, "parallel_setup_cost": 946.1659758067328, "parallel_tuple_cost": 2.1239178720370173, "quote_all_identifiers": "off", "random_page_cost": 7.41042183199986, "replacement_sort_tuples": 953411904, "seq_page_cost": 3.0938895616455007, "shared_buffers": 90115, "temp_buffers": 5793, "temp_file_limit": 3571346, "vacuum_cost_delay": 36, "vacuum_cost_limit": 9127, "vacuum_cost_page_dirty": 2275, "vacuum_cost_page_hit": 7363, "vacuum_cost_page_miss": 6409, "vacuum_freeze_min_age": 632385476, "vacuum_freeze_table_age": 696963060, "vacuum_multixact_freeze_min_age": 611569434, "vacuum_multixact_freeze_table_age": 725392639, "wal_buffers": 48379, "wal_compression": "on", "wal_log_hints": "off", "wal_writer_delay": 4075, "wal_writer_flush_after": 16464, "work_mem": 44227}, "budget": 0, "origin": "Local Search"}
